{
  "name": "Large Nether Rocky Island",
  "category": "skyseed:skyseeds",
  "icon": "minecraft:blackstone",
  "advancement": "skyseed:craft_nether_rocky_large",
  "pages": [
    { "type": "patchouli:text", "text": "The Nether Rocky island writ large — a broad deep-mining isle of netherrack over blackstone, with far more $(item)nether quartz$(), $(item)nether gold$(), $(item)gilded blackstone$() and $(item)ancient debris$() (richest near the lava sea)." },
    { "type": "patchouli:text", "text": "$(bold)Crafted$()$(br)A $(item)Large Rocky Skyseed$() in the centre of a 3x3 of $(item)netherrack$() and nether $(item)quartz$()." }
  ]
}
